{
    "search_metadata": {
        "id": "6256e0ebf0adfbac6d7f3052",
        "status": "Success",
        "json_endpoint": "https://serpapi.com/searches/b61dba387c7698da/6256e0ebf0adfbac6d7f3052.json",
        "created_at": "2022-04-13 14:40:43 UTC",
        "processed_at": "2022-04-13 14:40:43 UTC",
        "google_scholar_author_url": "https://scholar.google.com/citations?user=69pEM_YAAAAJ&hl=en&cstart=0&pagesize=100",
        "raw_html_file": "https://serpapi.com/searches/b61dba387c7698da/6256e0ebf0adfbac6d7f3052.html",
        "total_time_taken": 1.65,
        "total_articles": 67,
        "total_co_authors": 20
    },
    "search_parameters": {
        "engine": "google_scholar_author",
        "author_id": "69pEM_YAAAAJ",
        "hl": "en",
        "start": 0,
        "num": "100"
    },
    "author": {
        "name": "Raghava Mutharaju",
        "affiliations": "Assistant Professor, Computer Science and Engineering, IIIT-Delhi, India",
        "email": "Verified email at iiitd.ac.in",
        "website": "http://faculty.iiitd.ac.in/~raghavam",
        "interests": [
            {
                "title": "OWL Reasoning",
                "link": "https://scholar.google.com/citations?view_op=search_authors&hl=en&mauthors=label:owl_reasoning",
                "serpapi_link": "https://serpapi.com/search.json?engine=google_scholar_profiles&hl=en&mauthors=label%3Aowl_reasoning"
            },
            {
                "title": "Semantic Web",
                "link": "https://scholar.google.com/citations?view_op=search_authors&hl=en&mauthors=label:semantic_web",
                "serpapi_link": "https://serpapi.com/search.json?engine=google_scholar_profiles&hl=en&mauthors=label%3Asemantic_web"
            },
            {
                "title": "SPARQL query processing",
                "link": "https://scholar.google.com/citations?view_op=search_authors&hl=en&mauthors=label:sparql_query_processing",
                "serpapi_link": "https://serpapi.com/search.json?engine=google_scholar_profiles&hl=en&mauthors=label%3Asparql_query_processing"
            },
            {
                "title": "Knowledge Representation",
                "link": "https://scholar.google.com/citations?view_op=search_authors&hl=en&mauthors=label:knowledge_representation",
                "serpapi_link": "https://serpapi.com/search.json?engine=google_scholar_profiles&hl=en&mauthors=label%3Aknowledge_representation"
            }
        ],
        "thumbnail": "https://scholar.googleusercontent.com/citations?view_op=view_photo&user=69pEM_YAAAAJ&citpid=2"
    },
    "articles": [
        {
            "title": "Spatio-temporal-thematic analysis of citizen sensor data: Challenges and experiences",
            "link": "https://scholar.google.com/citations?view_op=view_citation&hl=en&user=69pEM_YAAAAJ&pagesize=100&citation_for_view=69pEM_YAAAAJ:u5HHmVD_uO8C",
            "citation_id": "69pEM_YAAAAJ:u5HHmVD_uO8C",
            "authors": "M Nagarajan, K Gomadam, AP Sheth, A Ranabahu, R Mutharaju, ...",
            "publication": "International Conference on Web Information Systems Engineering, 539-553, 2009",
            "cited_by": {
                "value": 134,
                "link": "https://scholar.google.com/scholar?oi=bibs&hl=en&cites=14541444962596178516",
                "serpapi_link": "https://serpapi.com/search.json?cites=14541444962596178516&engine=google_scholar&hl=en",
                "cites_id": "14541444962596178516"
            },
            "year": "2009"
        },
        {
            "title": "A MapReduce Algorithm for EL+",
            "link": "https://scholar.google.com/citations?view_op=view_citation&hl=en&user=69pEM_YAAAAJ&pagesize=100&citation_for_view=69pEM_YAAAAJ:u-x6o8ySG0sC",
            "citation_id": "69pEM_YAAAAJ:u-x6o8ySG0sC",
            "authors": "R Mutharaju, F Maier, P Hitzler",
            "publication": "23rd International Workshop on Description Logics DL2010, 456, 2010",
            "cited_by": {
                "value": 71,
                "link": "https://scholar.google.com/scholar?oi=bibs&hl=en&cites=6624370700402458883",
                "serpapi_link": "https://serpapi.com/search.json?cites=6624370700402458883&engine=google_scholar&hl=en",
                "cites_id": "6624370700402458883"
            },
            "year": "2010"
        },
        {
            "title": "Ontology-driven provenance management in escience: An application in parasite research",
            "link": "https://scholar.google.com/citations?view_op=view_citation&hl=en&user=69pEM_YAAAAJ&pagesize=100&citation_for_view=69pEM_YAAAAJ:d1gkVwhDpl0C",
            "citation_id": "69pEM_YAAAAJ:d1gkVwhDpl0C",
            "authors": "SS Sahoo, DB Weatherly, R Mutharaju, P Anantharam, A Sheth, ...",
            "publication": "OTM Confederated International Conferences\" On the Move to Meaningful \u2026, 2009",
            "cited_by": {
                "value": 35,
                "link": "https://scholar.google.com/scholar?oi=bibs&hl=en&cites=11168359759146307238",
                "serpapi_link": "https://serpapi.com/search.json?cites=11168359759146307238&engine=google_scholar&hl=en",
                "cites_id": "11168359759146307238"
            },
            "year": "2009"
        },
        {
            "title": "Linked Data: Storing, Querying, and Reasoning",
            "link": "https://scholar.google.com/citations?view_op=view_citation&hl=en&user=69pEM_YAAAAJ&pagesize=100&citation_for_view=69pEM_YAAAAJ:qUcmZB5y_30C",
            "citation_id": "69pEM_YAAAAJ:qUcmZB5y_30C",
            "authors": "S Sakr, M Wylot, R Mutharaju, D Le Phuoc, I Fundulaki",
            "publication": "Springer, 2018",
            "cited_by": {
                "value": 33,
                "link": "https://scholar.google.com/scholar?oi=bibs&hl=en&cites=3307078185710519656",
                "serpapi_link": "https://serpapi.com/search.json?cites=3307078185710519656&engine=google_scholar&hl=en",
                "cites_id": "3307078185710519656"
            },
            "year": "2018"
        },
        {
            "title": "D-SPARQ: Distributed, Scalable and Efficient RDF Query Engine",
            "link": "https://scholar.google.com/citations?view_op=view_citation&hl=en&user=69pEM_YAAAAJ&pagesize=100&citation_for_view=69pEM_YAAAAJ:Tyk-4Ss8FVUC",
            "citation_id": "69pEM_YAAAAJ:Tyk-4Ss8FVUC",
            "authors": "R Mutharaju, S Sakr, A Sala, P Hitzler",
            "publication": "The 12th International Semantic Web Conference (ISWC 2013), 261-264, 2013",
            "cited_by": {
                "value": 33,
                "link": "https://scholar.google.com/scholar?oi=bibs&hl=en&cites=4292302407250851903",
                "serpapi_link": "https://serpapi.com/search.json?cites=4292302407250851903&engine=google_scholar&hl=en",
                "cites_id": "4292302407250851903"
            },
            "year": "2013"
        },
        {
            "title": "A survey of large-scale reasoning on the web of data",
            "link": "https://scholar.google.com/citations?view_op=view_citation&hl=en&user=69pEM_YAAAAJ&pagesize=100&citation_for_view=69pEM_YAAAAJ:-f6ydRqryjwC",
            "citation_id": "69pEM_YAAAAJ:-f6ydRqryjwC",
            "authors": "G Antoniou, S Batsakis, R Mutharaju, JZ Pan, G Qi, I Tachmazidis, ...",
            "publication": "The Knowledge Engineering Review 33, 2018",
            "cited_by": {
                "value": 19,
                "link": "https://scholar.google.com/scholar?oi=bibs&hl=en&cites=3283832545650090707",
                "serpapi_link": "https://serpapi.com/search.json?cites=3283832545650090707&engine=google_scholar&hl=en",
                "cites_id": "3283832545650090707"
            },
            "year": "2018"
        },
        {
            "title": "Distributed and Scalable OWL EL Reasoning",
            "link": "https://scholar.google.com/citations?view_op=view_citation&hl=en&user=69pEM_YAAAAJ&pagesize=100&citation_for_view=69pEM_YAAAAJ:UebtZRa9Y70C",
            "citation_id": "69pEM_YAAAAJ:UebtZRa9Y70C",
            "authors": "R Mutharaju, P Hitzler, P Mateti, F L\u00e9cu\u00e9",
            "publication": "The 12th Extended Semantic Web Conference (ESWC 2015), 2015",
            "cited_by": {
                "value": 19,
                "link": "https://scholar.google.com/scholar?oi=bibs&hl=en&cites=17289948510426730657",
                "serpapi_link": "https://serpapi.com/search.json?cites=17289948510426730657&engine=google_scholar&hl=en",
                "cites_id": "17289948510426730657"
            },
            "year": "2015"
        },
        {
            "title": "DistEL: A distributed EL+ ontology classifier",
            "link": "https://scholar.google.com/citations?view_op=view_citation&hl=en&user=69pEM_YAAAAJ&pagesize=100&citation_for_view=69pEM_YAAAAJ:eQOLeE2rZwMC",
            "citation_id": "69pEM_YAAAAJ:eQOLeE2rZwMC",
            "authors": "R Mutharaju, P Hitzler, P Mateti",
            "publication": "9th International Workshop on Scalable Semantic Web Knowledge Base Systems \u2026, 2013",
            "cited_by": {
                "value": 18,
                "link": "https://scholar.google.com/scholar?oi=bibs&hl=en&cites=14365083702418592006",
                "serpapi_link": "https://serpapi.com/search.json?cites=14365083702418592006&engine=google_scholar&hl=en",
                "cites_id": "14365083702418592006"
            },
            "year": "2013"
        },
        {
            "title": "Reasoning with Fuzzy-EL+ Ontologies Using MapReduce",
            "link": "https://scholar.google.com/citations?view_op=view_citation&hl=en&user=69pEM_YAAAAJ&pagesize=100&citation_for_view=69pEM_YAAAAJ:2osOgNQ5qMEC",
            "citation_id": "69pEM_YAAAAJ:2osOgNQ5qMEC",
            "authors": "Z Zhou, G Qi, C Liu, P Hitzler, R Mutharaju",
            "publication": "ECAI 2012, 933-934, 2012",
            "cited_by": {
                "value": 18,
                "link": "https://scholar.google.com/scholar?oi=bibs&hl=en&cites=10495141943004693605",
                "serpapi_link": "https://serpapi.com/search.json?cites=10495141943004693605&engine=google_scholar&hl=en",
                "cites_id": "10495141943004693605"
            },
            "year": "2012"
        },
        {
            "title": "Very large scale owl reasoning through distributed computation",
            "link": "https://scholar.google.com/citations?view_op=view_citation&hl=en&user=69pEM_YAAAAJ&pagesize=100&citation_for_view=69pEM_YAAAAJ:UeHWp8X0CEIC",
            "citation_id": "69pEM_YAAAAJ:UeHWp8X0CEIC",
            "authors": "R Mutharaju",
            "publication": "International Semantic Web Conference, 407-414, 2012",
            "cited_by": {
                "value": 11,
                "link": "https://scholar.google.com/scholar?oi=bibs&hl=en&cites=16236411105366596348",
                "serpapi_link": "https://serpapi.com/search.json?cites=16236411105366596348&engine=google_scholar&hl=en",
                "cites_id": "16236411105366596348"
            },
            "year": "2012"
        },
        {
            "title": "Scale Reasoning with Fuzzy-EL+ Ontologies based on MapReduce",
            "link": "https://scholar.google.com/citations?view_op=view_citation&hl=en&user=69pEM_YAAAAJ&pagesize=100&citation_for_view=69pEM_YAAAAJ:_FxGoFyzp5QC",
            "citation_id": "69pEM_YAAAAJ:_FxGoFyzp5QC",
            "authors": "Z Zhou, G Qi, C Lui, P Hitzler, R Mutharaju",
            "publication": "Proceedings of the IJCAI-2013 Workshop on Weighted Logics for Artificial \u2026, 2013",
            "cited_by": {
                "value": 10,
                "link": "https://scholar.google.com/scholar?oi=bibs&hl=en&cites=4410907887366665796",
                "serpapi_link": "https://serpapi.com/search.json?cites=4410907887366665796&engine=google_scholar&hl=en",
                "cites_id": "4410907887366665796"
            },
            "year": "2013"
        },
        {
            "title": "Towards a Rule Based Distributed OWL Reasoning Framework",
            "link": "https://scholar.google.com/citations?view_op=view_citation&hl=en&user=69pEM_YAAAAJ&pagesize=100&citation_for_view=69pEM_YAAAAJ:3fE2CSJIrl8C",
            "citation_id": "69pEM_YAAAAJ:3fE2CSJIrl8C",
            "authors": "R Mutharaju, P Mateti, P Hitzler",
            "publication": "12th OWL Experiences and Directions Workshop (OWLED 2015) co-located with \u2026, 2015",
            "cited_by": {
                "value": 9,
                "link": "https://scholar.google.com/scholar?oi=bibs&hl=en&cites=4044449789414931796",
                "serpapi_link": "https://serpapi.com/search.json?cites=4044449789414931796&engine=google_scholar&hl=en",
                "cites_id": "4044449789414931796"
            },
            "year": "2015"
        },
        {
            "title": "Distributed Reasoning with EL++ using MapReduce",
            "link": "https://scholar.google.com/citations?view_op=view_citation&hl=en&user=69pEM_YAAAAJ&pagesize=100&citation_for_view=69pEM_YAAAAJ:WF5omc3nYNoC",
            "citation_id": "69pEM_YAAAAJ:WF5omc3nYNoC",
            "authors": "F Maier, R Mutharaju, P Hitzler",
            "publication": "Technical Report. Wright State University, Dayton, OH, USA., 2010",
            "cited_by": {
                "value": 9,
                "link": "https://scholar.google.com/scholar?oi=bibs&hl=en&cites=4745571076432570473",
                "serpapi_link": "https://serpapi.com/search.json?cites=4745571076432570473&engine=google_scholar&hl=en",
                "cites_id": "4745571076432570473"
            },
            "year": "2010"
        },
        {
            "title": "OWL2Bench: a benchmark for OWL 2 reasoners",
            "link": "https://scholar.google.com/citations?view_op=view_citation&hl=en&user=69pEM_YAAAAJ&pagesize=100&citation_for_view=69pEM_YAAAAJ:j3f4tGmQtD8C",
            "citation_id": "69pEM_YAAAAJ:j3f4tGmQtD8C",
            "authors": "G Singh, S Bhatia, R Mutharaju",
            "publication": "International Semantic Web Conference, 81-96, 2020",
            "cited_by": {
                "value": 8,
                "link": "https://scholar.google.com/scholar?oi=bibs&hl=en&cites=884783541291752395",
                "serpapi_link": "https://serpapi.com/search.json?cites=884783541291752395&engine=google_scholar&hl=en",
                "cites_id": "884783541291752395"
            },
            "year": "2020"
        },
        {
            "title": "Reasoning with large scale OWL 2 EL ontologies based on MapReduce",
            "link": "https://scholar.google.com/citations?view_op=view_citation&hl=en&user=69pEM_YAAAAJ&pagesize=100&citation_for_view=69pEM_YAAAAJ:_kc_bZDykSQC",
            "citation_id": "69pEM_YAAAAJ:_kc_bZDykSQC",
            "authors": "Z Zhou, G Qi, C Liu, R Mutharaju, P Hitzler",
            "publication": "Asia-Pacific Web Conference, 429-433, 2016",
            "cited_by": {
                "value": 8,
                "link": "https://scholar.google.com/scholar?oi=bibs&hl=en&cites=2616553229566758894",
                "serpapi_link": "https://serpapi.com/search.json?cites=2616553229566758894&engine=google_scholar&hl=en",
                "cites_id": "2616553229566758894"
            },
            "year": "2016"
        },
        {
            "title": "Social Signal Processing for Real-time Situational Understanding: a Vision and Approach",
            "link": "https://scholar.google.com/citations?view_op=view_citation&hl=en&user=69pEM_YAAAAJ&pagesize=100&citation_for_view=69pEM_YAAAAJ:8k81kl-MbHgC",
            "citation_id": "69pEM_YAAAAJ:8k81kl-MbHgC",
            "authors": "K Jayarajah, S Yao, R Mutharaju, A Misra, G De Mel, J Skipper, ...",
            "publication": "First International Workshop on Social Sensing (SocialSens 2015), 2015",
            "cited_by": {
                "value": 8,
                "link": "https://scholar.google.com/scholar?oi=bibs&hl=en&cites=12811870852029886136",
                "serpapi_link": "https://serpapi.com/search.json?cites=12811870852029886136&engine=google_scholar&hl=en",
                "cites_id": "12811870852029886136"
            },
            "year": "2015"
        },
        {
            "title": "Twitris: socially influenced browsing",
            "link": "https://scholar.google.com/citations?view_op=view_citation&hl=en&user=69pEM_YAAAAJ&pagesize=100&citation_for_view=69pEM_YAAAAJ:9yKSN-GCB0IC",
            "citation_id": "69pEM_YAAAAJ:9yKSN-GCB0IC",
            "authors": "AS Jadhav, W Wang, R Mutharaju, P Anantharam, V Nguyen, AP Sheth, ...",
            "publication": "Semantic Web Challenge at the 8th International Semantic Web Conference \u2026, 2009",
            "cited_by": {
                "value": 8,
                "link": "https://scholar.google.com/scholar?oi=bibs&hl=en&cites=11735189094472069012",
                "serpapi_link": "https://serpapi.com/search.json?cites=11735189094472069012&engine=google_scholar&hl=en",
                "cites_id": "11735189094472069012"
            },
            "year": "2009"
        },
        {
            "title": "Centralized RDF Query Processing",
            "link": "https://scholar.google.com/citations?view_op=view_citation&hl=en&user=69pEM_YAAAAJ&pagesize=100&citation_for_view=69pEM_YAAAAJ:dhFuZR0502QC",
            "citation_id": "69pEM_YAAAAJ:dhFuZR0502QC",
            "authors": "S Sakr, M Wylot, R Mutharaju, D Le Phuoc, I Fundulaki",
            "publication": "Linked Data, 33-49, 2018",
            "cited_by": {
                "value": 7,
                "link": "https://scholar.google.com/scholar?oi=bibs&hl=en&cites=6425980512458336528",
                "serpapi_link": "https://serpapi.com/search.json?cites=6425980512458336528&engine=google_scholar&hl=en",
                "cites_id": "6425980512458336528"
            },
            "year": "2018"
        },
        {
            "title": "Distributed rule-based ontology reasoning",
            "link": "https://scholar.google.com/citations?view_op=view_citation&hl=en&user=69pEM_YAAAAJ&pagesize=100&citation_for_view=69pEM_YAAAAJ:4TOpqqG69KYC",
            "citation_id": "69pEM_YAAAAJ:4TOpqqG69KYC",
            "authors": "R Mutharaju",
            "publication": "Wright State University, 2016",
            "cited_by": {
                "value": 7,
                "link": "https://scholar.google.com/scholar?oi=bibs&hl=en&cites=11319370617278303681",
                "serpapi_link": "https://serpapi.com/search.json?cites=11319370617278303681&engine=google_scholar&hl=en",
                "cites_id": "11319370617278303681"
            },
            "year": "2016"
        },
        {
            "title": "Distributed OWL EL Reasoning: The Story So Far",
            "link": "https://scholar.google.com/citations?view_op=view_citation&hl=en&user=69pEM_YAAAAJ&pagesize=100&citation_for_view=69pEM_YAAAAJ:ufrVoPGSRksC",
            "citation_id": "69pEM_YAAAAJ:ufrVoPGSRksC",
            "authors": "R Mutharaju, P Hitzler, P Mateti",
            "publication": "10th International Workshop on Scalable Semantic Web Knowledge Base Systems \u2026, 2014",
            "cited_by": {
                "value": 6,
                "link": "https://scholar.google.com/scholar?oi=bibs&hl=en&cites=7700536694399249387",
                "serpapi_link": "https://serpapi.com/search.json?cites=7700536694399249387&engine=google_scholar&hl=en",
                "cites_id": "7700536694399249387"
            },
            "year": "2014"
        },
        {
            "title": "Apparatus, system and method for providing an agent that intelligently solves information technology issues",
            "link": "https://scholar.google.com/citations?view_op=view_citation&hl=en&user=69pEM_YAAAAJ&pagesize=100&citation_for_view=69pEM_YAAAAJ:4JMBOYKVnBMC",
            "citation_id": "69pEM_YAAAAJ:4JMBOYKVnBMC",
            "authors": "VV Mulwad, I Bueno, VR Mutharaju",
            "publication": "US Patent 10,430,517, 2019",
            "cited_by": {
                "value": 3,
                "link": "https://scholar.google.com/scholar?oi=bibs&hl=en&cites=6509959988822133299",
                "serpapi_link": "https://serpapi.com/search.json?cites=6509959988822133299&engine=google_scholar&hl=en",
                "cites_id": "6509959988822133299"
            },
            "year": "2019"
        },
        {
            "title": "Distributed reasoning of rdf data",
            "link": "https://scholar.google.com/citations?view_op=view_citation&hl=en&user=69pEM_YAAAAJ&pagesize=100&citation_for_view=69pEM_YAAAAJ:ZeXyd9-uunAC",
            "citation_id": "69pEM_YAAAAJ:ZeXyd9-uunAC",
            "authors": "S Sakr, M Wylot, R Mutharaju, D Le Phuoc, I Fundulaki",
            "publication": "Linked Data, 109-126, 2018",
            "cited_by": {
                "value": 3,
                "link": "https://scholar.google.com/scholar?oi=bibs&hl=en&cites=16273608419083237935",
                "serpapi_link": "https://serpapi.com/search.json?cites=16273608419083237935&engine=google_scholar&hl=en",
                "cites_id": "16273608419083237935"
            },
            "year": "2018"
        },
        {
            "title": "Distributed RDF Query Processing",
            "link": "https://scholar.google.com/citations?view_op=view_citation&hl=en&user=69pEM_YAAAAJ&pagesize=100&citation_for_view=69pEM_YAAAAJ:QIV2ME_5wuYC",
            "citation_id": "69pEM_YAAAAJ:QIV2ME_5wuYC",
            "authors": "S Sakr, M Wylot, R Mutharaju, D Le Phuoc, I Fundulaki",
            "publication": "Linked Data, 51-83, 2018",
            "cited_by": {
                "value": 3,
                "link": "https://scholar.google.com/scholar?oi=bibs&hl=en&cites=6379510721493496724",
                "serpapi_link": "https://serpapi.com/search.json?cites=6379510721493496724&engine=google_scholar&hl=en",
                "cites_id": "6379510721493496724"
            },
            "year": "2018"
        },
        {
            "title": "OntoSeer: A Tool to Ease the Ontology Development Process",
            "link": "https://scholar.google.com/citations?view_op=view_citation&hl=en&user=69pEM_YAAAAJ&pagesize=100&citation_for_view=69pEM_YAAAAJ:iH-uZ7U-co4C",
            "citation_id": "69pEM_YAAAAJ:iH-uZ7U-co4C",
            "authors": "P Bhattacharyya, R Mutharaju",
            "publication": "8th ACM IKDD CODS and 26th COMAD, 428-428, 2021",
            "cited_by": {
                "value": 2,
                "link": "https://scholar.google.com/scholar?oi=bibs&hl=en&cites=9806804726354822343",
                "serpapi_link": "https://serpapi.com/search.json?cites=9806804726354822343&engine=google_scholar&hl=en",
                "cites_id": "9806804726354822343"
            },
            "year": "2021"
        },
        {
            "title": "Linked data",
            "link": "https://scholar.google.com/citations?view_op=view_citation&hl=en&user=69pEM_YAAAAJ&pagesize=100&citation_for_view=69pEM_YAAAAJ:Wp0gIr-vW9MC",
            "citation_id": "69pEM_YAAAAJ:Wp0gIr-vW9MC",
            "authors": "S Sakr, M Wylot, R Mutharaju, D Le Phuoc, I Fundulaki",
            "publication": "Springer: Cham 246, 33-49, 2018",
            "cited_by": {
                "value": 2,
                "link": "https://scholar.google.com/scholar?oi=bibs&hl=en&cites=5751265297441237337",
                "serpapi_link": "https://serpapi.com/search.json?cites=5751265297441237337&engine=google_scholar&hl=en",
                "cites_id": "5751265297441237337"
            },
            "year": "2018"
        },
        {
            "title": "EmEL++: Embeddings for EL++ Description Logic",
            "link": "https://scholar.google.com/citations?view_op=view_citation&hl=en&user=69pEM_YAAAAJ&pagesize=100&citation_for_view=69pEM_YAAAAJ:BqipwSGYUEgC",
            "citation_id": "69pEM_YAAAAJ:BqipwSGYUEgC",
            "authors": "S Mondal, S Bhatia, R Mutharaju",
            "publication": "AAAI 2021 Spring Symposium on Combining Machine Learning and Knowledge \u2026, 2021",
            "cited_by": {
                "value": 1,
                "link": "https://scholar.google.com/scholar?oi=bibs&hl=en&cites=7895806242494318677",
                "serpapi_link": "https://serpapi.com/search.json?cites=7895806242494318677&engine=google_scholar&hl=en",
                "cites_id": "7895806242494318677"
            },
            "year": "2021"
        },
        {
            "title": "EmEL++: Embeddings for\ue231\ue238 Description Logic",
            "link": "https://scholar.google.com/citations?view_op=view_citation&hl=en&user=69pEM_YAAAAJ&pagesize=100&citation_for_view=69pEM_YAAAAJ:NMxIlDl6LWMC",
            "citation_id": "69pEM_YAAAAJ:NMxIlDl6LWMC",
            "authors": "S Mondal, S Bhatia, R Mutharaju",
            "cited_by": {
                "value": 1,
                "link": "https://scholar.google.com/scholar?oi=bibs&hl=en&cites=6236957386575117899,17831999000463912357",
                "serpapi_link": "https://serpapi.com/search.json?cites=6236957386575117899%2C17831999000463912357&engine=google_scholar&hl=en",
                "cites_id": "6236957386575117899,17831999000463912357"
            },
            "year": "2021"
        },
        {
            "title": "A Benchmark for OWL 2 DL Reasoners",
            "link": "https://scholar.google.com/citations?view_op=view_citation&hl=en&user=69pEM_YAAAAJ&pagesize=100&citation_for_view=69pEM_YAAAAJ:RHpTSmoSYBkC",
            "citation_id": "69pEM_YAAAAJ:RHpTSmoSYBkC",
            "authors": "G Singh, S Bhatia, R Mutharaju",
            "publication": "Proceedings of the 7th ACM IKDD CoDS and 25th COMAD, 353-353, 2020",
            "cited_by": {
                "value": 1,
                "link": "https://scholar.google.com/scholar?oi=bibs&hl=en&cites=15426054906142507627",
                "serpapi_link": "https://serpapi.com/search.json?cites=15426054906142507627&engine=google_scholar&hl=en",
                "cites_id": "15426054906142507627"
            },
            "year": "2020"
        },
        {
            "title": "A recommendation system involving human-in-the-loop to improve the quality of ontologies",
            "link": "https://scholar.google.com/citations?view_op=view_citation&hl=en&user=69pEM_YAAAAJ&pagesize=100&citation_for_view=69pEM_YAAAAJ:lSLTfruPkqcC",
            "citation_id": "69pEM_YAAAAJ:lSLTfruPkqcC",
            "authors": "P Bhattacharyya, VR Mutharaju",
            "cited_by": {
                "value": 1,
                "link": "https://scholar.google.com/scholar?oi=bibs&hl=en&cites=14921338519179639478",
                "serpapi_link": "https://serpapi.com/search.json?cites=14921338519179639478&engine=google_scholar&hl=en",
                "cites_id": "14921338519179639478"
            },
            "year": "2020"
        },
        {
            "title": "ODPReco-A Tool to Recommend Ontology Design Patterns",
            "link": "https://scholar.google.com/citations?view_op=view_citation&hl=en&user=69pEM_YAAAAJ&pagesize=100&citation_for_view=69pEM_YAAAAJ:mB3voiENLucC",
            "citation_id": "69pEM_YAAAAJ:mB3voiENLucC",
            "authors": "MA Yasvi, R Mutharaju",
            "publication": "Workshop on Ontology Design Patterns (WOP) 2019, co-located with ISWC 2019 \u2026, 2019",
            "cited_by": {
                "value": 1,
                "link": "https://scholar.google.com/scholar?oi=bibs&hl=en&cites=11761837104640301049",
                "serpapi_link": "https://serpapi.com/search.json?cites=11761837104640301049&engine=google_scholar&hl=en",
                "cites_id": "11761837104640301049"
            },
            "year": "2019"
        },
        {
            "title": "Towards a Concurrent Approximate Description Logic Reasoner",
            "link": "https://scholar.google.com/citations?view_op=view_citation&hl=en&user=69pEM_YAAAAJ&pagesize=100&citation_for_view=69pEM_YAAAAJ:hFOr9nPyWt4C",
            "citation_id": "69pEM_YAAAAJ:hFOr9nPyWt4C",
            "authors": "RK Yadav, G Singh, R Mutharaju, S Bhatia",
            "publication": "International Semantic Web Conference (ISWC), Posters & Demos Track 2456 \u2026, 2019",
            "cited_by": {
                "value": 1,
                "link": "https://scholar.google.com/scholar?oi=bibs&hl=en&cites=14141044607398072838",
                "serpapi_link": "https://serpapi.com/search.json?cites=14141044607398072838&engine=google_scholar&hl=en",
                "cites_id": "14141044607398072838"
            },
            "year": "2019"
        },
        {
            "title": "Processing of RDF Stream Data",
            "link": "https://scholar.google.com/citations?view_op=view_citation&hl=en&user=69pEM_YAAAAJ&pagesize=100&citation_for_view=69pEM_YAAAAJ:7PzlFSSx8tAC",
            "citation_id": "69pEM_YAAAAJ:7PzlFSSx8tAC",
            "authors": "S Sakr, M Wylot, R Mutharaju, D Le Phuoc, I Fundulaki",
            "publication": "Linked Data, 85-108, 2018",
            "cited_by": {
                "value": 1,
                "link": "https://scholar.google.com/scholar?oi=bibs&hl=en&cites=7885758924793312623",
                "serpapi_link": "https://serpapi.com/search.json?cites=7885758924793312623&engine=google_scholar&hl=en",
                "cites_id": "7885758924793312623"
            },
            "year": "2018"
        },
        {
            "title": "Developing a Distributed Reasoner for the Semantic Web",
            "link": "https://scholar.google.com/citations?view_op=view_citation&hl=en&user=69pEM_YAAAAJ&pagesize=100&citation_for_view=69pEM_YAAAAJ:LkGwnXOMwfcC",
            "citation_id": "69pEM_YAAAAJ:LkGwnXOMwfcC",
            "authors": "R Mutharaju, P Mateti, P Hitzler",
            "publication": "Developers Workshop at the International Semantic Web Conference 2014, 2014",
            "cited_by": {
                "value": 1,
                "link": "https://scholar.google.com/scholar?oi=bibs&hl=en&cites=5896101090156681241",
                "serpapi_link": "https://serpapi.com/search.json?cites=5896101090156681241&engine=google_scholar&hl=en",
                "cites_id": "5896101090156681241"
            },
            "year": "2014"
        },
        {
            "title": "OntoSeer--A Recommendation System to Improve the Quality of Ontologies",
            "link": "https://scholar.google.com/citations?view_op=view_citation&hl=en&user=69pEM_YAAAAJ&pagesize=100&citation_for_view=69pEM_YAAAAJ:70eg2SAEIzsC",
            "citation_id": "69pEM_YAAAAJ:70eg2SAEIzsC",
            "authors": "P Bhattacharyya, R Mutharaju",
            "publication": "arXiv preprint arXiv:2202.02125, 2022",
            "cited_by": {
                "value": null,
                "link": "https://scholar.google.com"
            },
            "year": "2022"
        },
        {
            "title": "A SPARQL to Cypher Transpiler: Proposal and Initial Results",
            "link": "https://scholar.google.com/citations?view_op=view_citation&hl=en&user=69pEM_YAAAAJ&pagesize=100&citation_for_view=69pEM_YAAAAJ:35N4QoGY0k4C",
            "citation_id": "69pEM_YAAAAJ:35N4QoGY0k4C",
            "authors": "L A Agrawal, N Singhal, R Mutharaju",
            "publication": "5th Joint International Conference on Data Science & Management of Data (9th \u2026, 2022",
            "cited_by": {
                "value": null,
                "link": "https://scholar.google.com"
            },
            "year": "2022"
        },
        {
            "title": "SERC: Syntactic and Semantic Sequence based Event Relation Classification",
            "link": "https://scholar.google.com/citations?view_op=view_citation&hl=en&user=69pEM_YAAAAJ&pagesize=100&citation_for_view=69pEM_YAAAAJ:RGFaLdJalmkC",
            "citation_id": "69pEM_YAAAAJ:RGFaLdJalmkC",
            "authors": "K Venkatachalam, R Mutharaju, S Bhatia",
            "publication": "2021 IEEE 33rd International Conference on Tools with Artificial \u2026, 2021",
            "cited_by": {
                "value": null,
                "link": "https://scholar.google.com"
            },
            "year": "2021"
        },
        {
            "title": "Why Settle for Just One? Extending EL++ Ontology Embeddings with Many-to-Many Relationships",
            "link": "https://scholar.google.com/citations?view_op=view_citation&hl=en&user=69pEM_YAAAAJ&pagesize=100&citation_for_view=69pEM_YAAAAJ:ns9cj8rnVeAC",
            "citation_id": "69pEM_YAAAAJ:ns9cj8rnVeAC",
            "authors": "B Mohapatra, S Bhatia, R Mutharaju, G Srinivasaraghavan",
            "publication": "arXiv preprint arXiv:2110.10555, 2021",
            "cited_by": {
                "value": null,
                "link": "https://scholar.google.com"
            },
            "year": "2021"
        },
        {
            "title": "An Ontology Design Pattern for Modeling Bias",
            "link": "https://scholar.google.com/citations?view_op=view_citation&hl=en&user=69pEM_YAAAAJ&pagesize=100&citation_for_view=69pEM_YAAAAJ:maZDTaKrznsC",
            "citation_id": "69pEM_YAAAAJ:maZDTaKrznsC",
            "authors": "AM Kaushik, R Mutharaju",
            "publication": "Advances in Pattern-Based Ontology Engineering 51, 337, 2021",
            "cited_by": {
                "value": null,
                "link": "https://scholar.google.com"
            },
            "year": "2021"
        },
        {
            "title": "Extraction of Union and Intersection Axioms from Biomedical Text",
            "link": "https://scholar.google.com/citations?view_op=view_citation&hl=en&user=69pEM_YAAAAJ&pagesize=100&citation_for_view=69pEM_YAAAAJ:isC4tDSrTZIC",
            "citation_id": "69pEM_YAAAAJ:isC4tDSrTZIC",
            "authors": "N Sachdeva, M Jain, R Mutharaju",
            "publication": "Extended Semantic Web Conference (ESWC), Posters & Demos Track, 2021",
            "cited_by": {
                "value": null,
                "link": "https://scholar.google.com"
            },
            "year": "2021"
        },
        {
            "title": "Feature Fused Human Activity Recognition Network (FFHAR-Net)",
            "link": "https://scholar.google.com/citations?view_op=view_citation&hl=en&user=69pEM_YAAAAJ&pagesize=100&citation_for_view=69pEM_YAAAAJ:O3NaXMp0MMsC",
            "citation_id": "69pEM_YAAAAJ:O3NaXMp0MMsC",
            "authors": "A Singhal, M Goyal, J Shukla, R Mutharaju",
            "publication": "23rd International Conference on Human-Computer Interaction (HCI International), 2021",
            "cited_by": {
                "value": null,
                "link": "https://scholar.google.com"
            },
            "year": "2021"
        },
        {
            "title": "An Ontology Design Pattern Recommendation System",
            "link": "https://scholar.google.com/citations?view_op=view_citation&hl=en&user=69pEM_YAAAAJ&pagesize=100&citation_for_view=69pEM_YAAAAJ:GnPB-g6toBAC",
            "citation_id": "69pEM_YAAAAJ:GnPB-g6toBAC",
            "authors": "MA Yasvi, R Mutharaju",
            "publication": "Advances in Pattern-Based Ontology Engineering, 258-272, 2021",
            "cited_by": {
                "value": null,
                "link": "https://scholar.google.com"
            },
            "year": "2021"
        },
        {
            "title": "Advances in Pattern-Based Ontology Engineering",
            "link": "https://scholar.google.com/citations?view_op=view_citation&hl=en&user=69pEM_YAAAAJ&pagesize=100&citation_for_view=69pEM_YAAAAJ:M3NEmzRMIkIC",
            "citation_id": "69pEM_YAAAAJ:M3NEmzRMIkIC",
            "authors": "E Blomqvist, T Hahmann, K Hammar, P Hitzler, R Hoekstra, R Mutharaju, ...",
            "publication": "IOS Press, 2021",
            "cited_by": {
                "value": null,
                "link": "https://scholar.google.com"
            },
            "year": "2021"
        },
        {
            "title": "OWL2Bench: Towards a Customizable Benchmark for OWL 2 Reasoners",
            "link": "https://scholar.google.com/citations?view_op=view_citation&hl=en&user=69pEM_YAAAAJ&pagesize=100&citation_for_view=69pEM_YAAAAJ:r0BpntZqJG4C",
            "citation_id": "69pEM_YAAAAJ:r0BpntZqJG4C",
            "authors": "G Singh, A Kumar, K Bhagat, S Bhatia, R Mutharaju",
            "publication": "International Semantic Web Conference (ISWC), Posters & Demos Track 2721 \u2026, 2020",
            "cited_by": {
                "value": null,
                "link": "https://scholar.google.com"
            },
            "year": "2020"
        },
        {
            "title": "Ontology learning from text",
            "link": "https://scholar.google.com/citations?view_op=view_citation&hl=en&user=69pEM_YAAAAJ&pagesize=100&citation_for_view=69pEM_YAAAAJ:JV2RwH3_ST0C",
            "citation_id": "69pEM_YAAAAJ:JV2RwH3_ST0C",
            "authors": "N Sachdeva, VR Mutharaju",
            "publication": "IIIT-Delhi, 2020",
            "cited_by": {
                "value": null,
                "link": "https://scholar.google.com"
            },
            "year": "2020"
        },
        {
            "title": "Knowledge graph construction from text",
            "link": "https://scholar.google.com/citations?view_op=view_citation&hl=en&user=69pEM_YAAAAJ&pagesize=100&citation_for_view=69pEM_YAAAAJ:vV6vV6tmYwMC",
            "citation_id": "69pEM_YAAAAJ:vV6vV6tmYwMC",
            "authors": "V Saini, VR Mutharaju, T Chakraborty",
            "publication": "IIIT-Delhi, 2020",
            "cited_by": {
                "value": null,
                "link": "https://scholar.google.com"
            },
            "year": "2020"
        },
        {
            "title": "Knowledge graphs In medical domain",
            "link": "https://scholar.google.com/citations?view_op=view_citation&hl=en&user=69pEM_YAAAAJ&pagesize=100&citation_for_view=69pEM_YAAAAJ:blknAaTinKkC",
            "citation_id": "69pEM_YAAAAJ:blknAaTinKkC",
            "authors": "G Anand, RR Shah, VR Mutharaju",
            "publication": "IIIT-Delhi, 2020",
            "cited_by": {
                "value": null,
                "link": "https://scholar.google.com"
            },
            "year": "2020"
        },
        {
            "title": "Cardinality Extraction from Text for Ontology Learning",
            "link": "https://scholar.google.com/citations?view_op=view_citation&hl=en&user=69pEM_YAAAAJ&pagesize=100&citation_for_view=69pEM_YAAAAJ:R3hNpaxXUhUC",
            "citation_id": "69pEM_YAAAAJ:R3hNpaxXUhUC",
            "authors": "M Jain, P Mirza, R Mutharaju",
            "publication": "Proceedings of the 7th ACM IKDD CoDS and 25th COMAD, 354-354, 2020",
            "cited_by": {
                "value": null,
                "link": "https://scholar.google.com"
            },
            "year": "2020"
        },
        {
            "title": "Embeddings for the EL++ description logic",
            "link": "https://scholar.google.com/citations?view_op=view_citation&hl=en&user=69pEM_YAAAAJ&pagesize=100&citation_for_view=69pEM_YAAAAJ:TFP_iSt0sucC",
            "citation_id": "69pEM_YAAAAJ:TFP_iSt0sucC",
            "authors": "S Mondal, VR Mutharaju, S Bhatia",
            "publication": "IIIT-Delhi, 2020",
            "cited_by": {
                "value": null,
                "link": "https://scholar.google.com"
            },
            "year": "2020"
        },
        {
            "title": "Finding textual description for paths in knowledge graphs",
            "link": "https://scholar.google.com/citations?view_op=view_citation&hl=en&user=69pEM_YAAAAJ&pagesize=100&citation_for_view=69pEM_YAAAAJ:RYcK_YlVTxYC",
            "citation_id": "69pEM_YAAAAJ:RYcK_YlVTxYC",
            "authors": "D Agrawal, SP Kumar, S Bhatia, VR Mutharaju",
            "publication": "IIIT-Delhi, 2019",
            "cited_by": {
                "value": null,
                "link": "https://scholar.google.com"
            },
            "year": "2019"
        },
        {
            "title": "Knowledge Graph Technology and Applications Chairs\u2019 Welcome",
            "link": "https://scholar.google.com/citations?view_op=view_citation&hl=en&user=69pEM_YAAAAJ&pagesize=100&citation_for_view=69pEM_YAAAAJ:TQgYirikUcIC",
            "citation_id": "69pEM_YAAAAJ:TQgYirikUcIC",
            "authors": "Y Ding, C Xiong, R Mutharaju",
            "publication": "KGTA workshop co-located with TheWeb (WWW) 2019, 2019",
            "cited_by": {
                "value": null,
                "link": "https://scholar.google.com"
            },
            "year": "2019"
        },
        {
            "title": "Benchmarking RDF Query Engines and Instance Matching Systems",
            "link": "https://scholar.google.com/citations?view_op=view_citation&hl=en&user=69pEM_YAAAAJ&pagesize=100&citation_for_view=69pEM_YAAAAJ:L8Ckcad2t8MC",
            "citation_id": "69pEM_YAAAAJ:L8Ckcad2t8MC",
            "authors": "S Sakr, M Wylot, R Mutharaju, D Le Phuoc, I Fundulaki",
            "publication": "Linked Data, 127-179, 2018",
            "cited_by": {
                "value": null,
                "link": "https://scholar.google.com"
            },
            "year": "2018"
        },
        {
            "title": "Provenance Management for Linked Data",
            "link": "https://scholar.google.com/citations?view_op=view_citation&hl=en&user=69pEM_YAAAAJ&pagesize=100&citation_for_view=69pEM_YAAAAJ:mVmsd5A6BfQC",
            "citation_id": "69pEM_YAAAAJ:mVmsd5A6BfQC",
            "authors": "S Sakr, M Wylot, R Mutharaju, D Le Phuoc, I Fundulaki",
            "publication": "Linked Data, 181-195, 2018",
            "cited_by": {
                "value": null,
                "link": "https://scholar.google.com"
            },
            "year": "2018"
        },
        {
            "title": "Industrial Knowledge Graphs Workshop 2017: co-located with the 9th International ACM Web Science Conference 2017 (Preface; part of Content)",
            "link": "https://scholar.google.com/citations?view_op=view_citation&hl=en&user=69pEM_YAAAAJ&pagesize=100&citation_for_view=69pEM_YAAAAJ:hC7cP41nSMkC",
            "citation_id": "69pEM_YAAAAJ:hC7cP41nSMkC",
            "authors": "V Mulwad, R Mutharaju",
            "publication": "Proceedings of the 2017 ACM on Web Science Conference, 423-424, 2017",
            "cited_by": {
                "value": null,
                "link": "https://scholar.google.com"
            },
            "year": "2017"
        },
        {
            "title": "AI for Traffic Analytics",
            "link": "https://scholar.google.com/citations?view_op=view_citation&hl=en&user=69pEM_YAAAAJ&pagesize=100&citation_for_view=69pEM_YAAAAJ:M3ejUd6NZC8C",
            "citation_id": "69pEM_YAAAAJ:M3ejUd6NZC8C",
            "authors": "R Mutharaju, F L\u00e9cu\u00e9, JZ Pan, J Wu, P Hitzler",
            "publication": "IEEE Intelligent Informatics Bulletin 17, 21-26, 2016",
            "cited_by": {
                "value": null,
                "link": "https://scholar.google.com"
            },
            "year": "2016"
        },
        {
            "title": "Approximate description logic reasoning",
            "link": "https://scholar.google.com/citations?view_op=view_citation&hl=en&user=69pEM_YAAAAJ&pagesize=100&citation_for_view=69pEM_YAAAAJ:hMod-77fHWUC",
            "citation_id": "69pEM_YAAAAJ:hMod-77fHWUC",
            "authors": "RK Yadav, VR Mutharaju, S Bhatia",
            "publication": "IIIT-Delhi, 2015",
            "cited_by": {
                "value": null,
                "link": "https://scholar.google.com"
            },
            "year": "2015"
        },
        {
            "title": "Proceedings of the 1st International Diversity++ Workshop co-located with the 14th International Semantic Web Conference (ISWC 2015)",
            "link": "https://scholar.google.com/citations?view_op=view_citation&hl=en&user=69pEM_YAAAAJ&pagesize=100&citation_for_view=69pEM_YAAAAJ:kNdYIx-mwKoC",
            "citation_id": "69pEM_YAAAAJ:kNdYIx-mwKoC",
            "authors": "C d'Amato, F L\u00e9cu\u00e9, R Mutharaju, T Narock, F Wirth",
            "publication": "CEUR Workshop Proceedings 1501, 2015",
            "cited_by": {
                "value": null,
                "link": "https://scholar.google.com"
            },
            "year": "2015"
        },
        {
            "title": "Distributed Reasoning over Ontology Streams and Large Knowledge Base",
            "link": "https://scholar.google.com/citations?view_op=view_citation&hl=en&user=69pEM_YAAAAJ&pagesize=100&citation_for_view=69pEM_YAAAAJ:MXK_kJrjxJIC",
            "citation_id": "69pEM_YAAAAJ:MXK_kJrjxJIC",
            "authors": "R Mutharaju",
            "publication": "NSF Data Science Workshop 2015, 2015",
            "cited_by": {
                "value": null,
                "link": "https://scholar.google.com"
            },
            "year": "2015"
        },
        {
            "title": "Are We Really Standing on the Shoulders of Giants?",
            "link": "https://scholar.google.com/citations?view_op=view_citation&hl=en&user=69pEM_YAAAAJ&pagesize=100&citation_for_view=69pEM_YAAAAJ:hqOjcs7Dif8C",
            "citation_id": "69pEM_YAAAAJ:hqOjcs7Dif8C",
            "authors": "R Mutharaju, P Kapanipathi",
            "publication": "Workshop on Negative or Inconclusive Results in Semantic Web (NoISE 2015) at \u2026, 2015",
            "cited_by": {
                "value": null,
                "link": "https://scholar.google.com"
            },
            "year": "2015"
        },
        {
            "title": "Konf Connect",
            "link": "https://scholar.google.com/citations?view_op=view_citation&hl=en&user=69pEM_YAAAAJ&pagesize=100&citation_for_view=69pEM_YAAAAJ:0EnyYjriUFMC",
            "citation_id": "69pEM_YAAAAJ:0EnyYjriUFMC",
            "authors": "D Carral, A Joshi, A Krisnadhi, R Mutharaju, S Kunal, C Wang",
            "publication": "Metadata Challenge at the 21st International Conference on World Wide Web \u2026, 2012",
            "cited_by": {
                "value": null,
                "link": "https://scholar.google.com"
            },
            "year": "2012"
        },
        {
            "title": "How I Would Like Semantic Web To Be, For My Children.",
            "link": "https://scholar.google.com/citations?view_op=view_citation&hl=en&user=69pEM_YAAAAJ&pagesize=100&citation_for_view=69pEM_YAAAAJ:IjCSPb-OGe4C",
            "citation_id": "69pEM_YAAAAJ:IjCSPb-OGe4C",
            "authors": "R Mutharaju",
            "publication": "What will the Semantic Web look like 10 years from now? In conjunction with \u2026, 2012",
            "cited_by": {
                "value": null,
                "link": "https://scholar.google.com"
            },
            "year": "2012"
        },
        {
            "title": "Ontology Driven Integration of Biology Experiment Data",
            "link": "https://scholar.google.com/citations?view_op=view_citation&hl=en&user=69pEM_YAAAAJ&pagesize=100&citation_for_view=69pEM_YAAAAJ:Se3iqnhoufwC",
            "citation_id": "69pEM_YAAAAJ:Se3iqnhoufwC",
            "authors": "R Mutharaju, SS Sahoo, DB Weatherly, P Anantharam, F Logan, ...",
            "publication": "Ohio Collaborative Conference on BioInformatics (OCCBIO 2009), 2009",
            "cited_by": {
                "value": null,
                "link": "https://scholar.google.com"
            },
            "year": "2009"
        },
        {
            "title": "Trykipedia: Collaborative Bio-Ontology Development using Wiki Environment",
            "link": "https://scholar.google.com/citations?view_op=view_citation&hl=en&user=69pEM_YAAAAJ&pagesize=100&citation_for_view=69pEM_YAAAAJ:roLk4NBRz8UC",
            "citation_id": "69pEM_YAAAAJ:roLk4NBRz8UC",
            "authors": "P Anantharam, SS Sahoo, B Weatherly, F Logan, R Mutharaju, AP Sheth, ...",
            "publication": "Ohio Collaborative Conference on BioInformatics (OCCBIO 2009), 2009",
            "cited_by": {
                "value": null,
                "link": "https://scholar.google.com"
            },
            "year": "2009"
        },
        {
            "title": "Traceability from Use Case to .NET Assembly via Design Patterns",
            "link": "https://scholar.google.com/citations?view_op=view_citation&hl=en&user=69pEM_YAAAAJ&pagesize=100&citation_for_view=69pEM_YAAAAJ:5nxA0vEk-isC",
            "citation_id": "69pEM_YAAAAJ:5nxA0vEk-isC",
            "authors": "R Mutharaju, BD Chaudhary",
            "publication": "Technical Report. Motilal Nehru National Institute of Technology (MNNIT \u2026, 2006",
            "cited_by": {
                "value": null,
                "link": "https://scholar.google.com"
            },
            "year": "2006"
        },
        {
            "title": "An Ontology Design Pattern for Modeling Pollution",
            "link": "https://scholar.google.com/citations?view_op=view_citation&hl=en&user=69pEM_YAAAAJ&pagesize=100&citation_for_view=69pEM_YAAAAJ:NaGl4SEjCO4C",
            "citation_id": "69pEM_YAAAAJ:NaGl4SEjCO4C",
            "authors": "R Mutharaju",
            "cited_by": {
                "value": null,
                "link": "https://scholar.google.com"
            },
            "year": ""
        },
        {
            "title": "VU Research Portal",
            "link": "https://scholar.google.com/citations?view_op=view_citation&hl=en&user=69pEM_YAAAAJ&pagesize=100&citation_for_view=69pEM_YAAAAJ:YFjsv_pBGBYC",
            "citation_id": "69pEM_YAAAAJ:YFjsv_pBGBYC",
            "authors": "AE Antoniou, S Batsakis, R Mutharaju, JZ Pan, G Qi, I Tachmazidis, ...",
            "publication": "The Knowledge Engineering Review 33 (e21), 1-43, 0",
            "cited_by": {
                "value": null,
                "link": "https://scholar.google.com"
            },
            "year": ""
        },
        {
            "title": "ICDIS 2020",
            "link": "https://scholar.google.com/citations?view_op=view_citation&hl=en&user=69pEM_YAAAAJ&pagesize=100&citation_for_view=69pEM_YAAAAJ:bEWYMUwI8FkC",
            "citation_id": "69pEM_YAAAAJ:bEWYMUwI8FkC",
            "authors": "A Ganguly, A Turky, B Siddique, B Xue, BK Lee, C Bastos, C Bae, C Shen, ...",
            "cited_by": {
                "value": null,
                "link": "https://scholar.google.com"
            },
            "year": ""
        },
        {
            "title": "Spatio-Temporal-Thematic Analysis of Citizen Sensor Data",
            "link": "https://scholar.google.com/citations?view_op=view_citation&hl=en&user=69pEM_YAAAAJ&pagesize=100&citation_for_view=69pEM_YAAAAJ:4DMP91E08xMC",
            "citation_id": "69pEM_YAAAAJ:4DMP91E08xMC",
            "authors": "M Nagarajan, K Gomadam, A Sheth, A Ranabahu, R Mutharaju, A Jadhav",
            "cited_by": {
                "value": null,
                "link": "https://scholar.google.com"
            },
            "year": ""
        }
    ],
    "cited_by": {
        "table": [
            {
                "citations": {
                    "all": 492,
                    "since_2017": 217
                }
            },
            {
                "h_index": {
                    "all": 10,
                    "since_2017": 7
                }
            },
            {
                "i10_index": {
                    "all": 11,
                    "since_2017": 5
                }
            }
        ],
        "graph": [
            {
                "year": 2009,
                "citations": 3
            },
            {
                "year": 2010,
                "citations": 18
            },
            {
                "year": 2011,
                "citations": 31
            },
            {
                "year": 2012,
                "citations": 31
            },
            {
                "year": 2013,
                "citations": 44
            },
            {
                "year": 2014,
                "citations": 49
            },
            {
                "year": 2015,
                "citations": 49
            },
            {
                "year": 2016,
                "citations": 39
            },
            {
                "year": 2017,
                "citations": 30
            },
            {
                "year": 2018,
                "citations": 60
            },
            {
                "year": 2019,
                "citations": 26
            },
            {
                "year": 2020,
                "citations": 51
            },
            {
                "year": 2021,
                "citations": 39
            },
            {
                "year": 2022,
                "citations": 10
            }
        ]
    },
    "public_access": {
        "link": "https://scholar.google.com/citations?view_op=list_mandates&hl=en&user=69pEM_YAAAAJ",
        "available": 2,
        "not_available": 0
    },
    "co_authors": [
        {
            "name": "Pascal Hitzler",
            "link": "https://scholar.google.com/citations?user=EkwfQcMAAAAJ&hl=en",
            "serpapi_link": "https://serpapi.com/search.json?author_id=EkwfQcMAAAAJ&engine=google_scholar_author&hl=en&num=100&start=0",
            "author_id": "EkwfQcMAAAAJ",
            "affiliations": "Lloyd T. Smith Creativity in Engineering Chair, Kansas State University, Manhattan, Kansas",
            "email": "Verified email at ksu.edu",
            "thumbnail": "https://scholar.googleusercontent.com/citations?view_op=small_photo&user=EkwfQcMAAAAJ&citpid=9"
        },
        {
            "name": "Sherif Sakr",
            "link": "https://scholar.google.com/citations?user=0GSdV8IAAAAJ&hl=en",
            "serpapi_link": "https://serpapi.com/search.json?author_id=0GSdV8IAAAAJ&engine=google_scholar_author&hl=en&num=100&start=0",
            "author_id": "0GSdV8IAAAAJ",
            "affiliations": "UT, KSAU-HS, UNSW",
            "email": "Verified email at ut.ee",
            "thumbnail": "https://scholar.googleusercontent.com/citations?view_op=small_photo&user=0GSdV8IAAAAJ&citpid=2"
        },
        {
            "name": "Amit Sheth",
            "link": "https://scholar.google.com/citations?user=2T3H4ekAAAAJ&hl=en",
            "serpapi_link": "https://serpapi.com/search.json?author_id=2T3H4ekAAAAJ&engine=google_scholar_author&hl=en&num=100&start=0",
            "author_id": "2T3H4ekAAAAJ",
            "affiliations": "Director, AI Institute, University of South Carolina",
            "email": "Verified email at sc.edu",
            "thumbnail": "https://scholar.googleusercontent.com/citations?view_op=small_photo&user=2T3H4ekAAAAJ&citpid=4"
        },
        {
            "name": "Danh Le Phuoc",
            "link": "https://scholar.google.com/citations?user=7-k4HCoAAAAJ&hl=en",
            "serpapi_link": "https://serpapi.com/search.json?author_id=7-k4HCoAAAAJ&engine=google_scholar_author&hl=en&num=100&start=0",
            "author_id": "7-k4HCoAAAAJ",
            "affiliations": "Group Leader and Principle Investigator at Technical University of Berlin",
            "email": "Verified email at tu-berlin.de",
            "thumbnail": "https://scholar.googleusercontent.com/citations?view_op=small_photo&user=7-k4HCoAAAAJ&citpid=4"
        },
        {
            "name": "Irini Fundulaki",
            "link": "https://scholar.google.com/citations?user=ldj4sHYAAAAJ&hl=en",
            "serpapi_link": "https://serpapi.com/search.json?author_id=ldj4sHYAAAAJ&engine=google_scholar_author&hl=en&num=100&start=0",
            "author_id": "ldj4sHYAAAAJ",
            "affiliations": "Principal Researcher, Institute of Computer Science, FORTH",
            "email": "Verified email at ics.forth.gr",
            "thumbnail": "https://scholar.google.com/citations/images/avatar_scholar_56.png"
        },
        {
            "name": "Marcin Wylot",
            "link": "https://scholar.google.com/citations?user=hDIFc7UAAAAJ&hl=en",
            "serpapi_link": "https://serpapi.com/search.json?author_id=hDIFc7UAAAAJ&engine=google_scholar_author&hl=en&num=100&start=0",
            "author_id": "hDIFc7UAAAAJ",
            "email": "Verified email at tu-berlin.de",
            "thumbnail": "https://scholar.googleusercontent.com/citations?view_op=small_photo&user=hDIFc7UAAAAJ&citpid=4"
        },
        {
            "name": "Meena Nagarajan",
            "link": "https://scholar.google.com/citations?user=MqYog5sAAAAJ&hl=en",
            "serpapi_link": "https://serpapi.com/search.json?author_id=MqYog5sAAAAJ&engine=google_scholar_author&hl=en&num=100&start=0",
            "author_id": "MqYog5sAAAAJ",
            "affiliations": "Facebook",
            "email": "Verified email at fb.com",
            "thumbnail": "https://scholar.google.com/citations/images/avatar_scholar_56.png"
        },
        {
            "name": "Ajith Ranabahu",
            "link": "https://scholar.google.com/citations?user=YB9-iLQAAAAJ&hl=en",
            "serpapi_link": "https://serpapi.com/search.json?author_id=YB9-iLQAAAAJ&engine=google_scholar_author&hl=en&num=100&start=0",
            "author_id": "YB9-iLQAAAAJ",
            "affiliations": "Software Engineer / PhD, Amazon Web Service",
            "email": "Verified email at knoesis.org",
            "thumbnail": "https://scholar.googleusercontent.com/citations?view_op=small_photo&user=YB9-iLQAAAAJ&citpid=3"
        },
        {
            "name": "Karthik Gomadam",
            "link": "https://scholar.google.com/citations?user=an7BPvUAAAAJ&hl=en",
            "serpapi_link": "https://serpapi.com/search.json?author_id=an7BPvUAAAAJ&engine=google_scholar_author&hl=en&num=100&start=0",
            "author_id": "an7BPvUAAAAJ",
            "affiliations": "Data Architect, Castlighthealth",
            "email": "Verified email at castlighthealth.com",
            "thumbnail": "https://scholar.googleusercontent.com/citations?view_op=small_photo&user=an7BPvUAAAAJ&citpid=5"
        },
        {
            "name": "Ashutosh Jadhav",
            "link": "https://scholar.google.com/citations?user=dLePaxAAAAAJ&hl=en",
            "serpapi_link": "https://serpapi.com/search.json?author_id=dLePaxAAAAAJ&engine=google_scholar_author&hl=en&num=100&start=0",
            "author_id": "dLePaxAAAAAJ",
            "affiliations": "Research Staff Member at IBM Research, Almaden, California",
            "email": "Verified email at us.ibm.com",
            "thumbnail": "https://scholar.googleusercontent.com/citations?view_op=small_photo&user=dLePaxAAAAAJ&citpid=4"
        },
        {
            "name": "Sumit Bhatia",
            "link": "https://scholar.google.com/citations?user=8HVTWNkAAAAJ&hl=en",
            "serpapi_link": "https://serpapi.com/search.json?author_id=8HVTWNkAAAAJ&engine=google_scholar_author&hl=en&num=100&start=0",
            "author_id": "8HVTWNkAAAAJ",
            "affiliations": "Senior ML Scientist, Adobe Inc.",
            "email": "Verified email at adobe.com",
            "thumbnail": "https://scholar.googleusercontent.com/citations?view_op=small_photo&user=8HVTWNkAAAAJ&citpid=9"
        },
        {
            "name": "Frederick Maier",
            "link": "https://scholar.google.com/citations?user=Tj47doAAAAAJ&hl=en",
            "serpapi_link": "https://serpapi.com/search.json?author_id=Tj47doAAAAAJ&engine=google_scholar_author&hl=en&num=100&start=0",
            "author_id": "Tj47doAAAAAJ",
            "affiliations": "University of Georgia",
            "email": "Verified email at uga.edu",
            "thumbnail": "https://scholar.google.com/citations/images/avatar_scholar_56.png"
        },
        {
            "name": "Pramod Anantharam",
            "link": "https://scholar.google.com/citations?user=yQ52qVkAAAAJ&hl=en",
            "serpapi_link": "https://serpapi.com/search.json?author_id=yQ52qVkAAAAJ&engine=google_scholar_author&hl=en&num=100&start=0",
            "author_id": "yQ52qVkAAAAJ",
            "affiliations": "Applied Researcher, Machine Learning, Robert Bosch LLC",
            "email": "Verified email at knoesis.org",
            "thumbnail": "https://scholar.googleusercontent.com/citations?view_op=small_photo&user=yQ52qVkAAAAJ&citpid=3"
        },
        {
            "name": "Gunjan Singh",
            "link": "https://scholar.google.com/citations?user=svepziAAAAAJ&hl=en",
            "serpapi_link": "https://serpapi.com/search.json?author_id=svepziAAAAAJ&engine=google_scholar_author&hl=en&num=100&start=0",
            "author_id": "svepziAAAAAJ",
            "affiliations": "Ph. D Student, Indraprastha Institute of Information Technology, Delhi, India",
            "email": "Verified email at iiitd.ac.in",
            "thumbnail": "https://scholar.google.com/citations/images/avatar_scholar_56.png"
        },
        {
            "name": "Satya Sahoo",
            "link": "https://scholar.google.com/citations?user=Lmj2JBUAAAAJ&hl=en",
            "serpapi_link": "https://serpapi.com/search.json?author_id=Lmj2JBUAAAAJ&engine=google_scholar_author&hl=en&num=100&start=0",
            "author_id": "Lmj2JBUAAAAJ",
            "affiliations": "Medical Informatics and Computer Science, Case Western Reserve University",
            "email": "Verified email at case.edu",
            "thumbnail": "https://scholar.googleusercontent.com/citations?view_op=small_photo&user=Lmj2JBUAAAAJ&citpid=6"
        },
        {
            "name": "Rick Tarleton",
            "link": "https://scholar.google.com/citations?user=jdtWLEEAAAAJ&hl=en",
            "serpapi_link": "https://serpapi.com/search.json?author_id=jdtWLEEAAAAJ&engine=google_scholar_author&hl=en&num=100&start=0",
            "author_id": "jdtWLEEAAAAJ",
            "affiliations": "Distinguished Research Professor, University of Georgia",
            "email": "Verified email at uga.edu",
            "thumbnail": "https://scholar.google.com/citations/images/avatar_scholar_56.png"
        },
        {
            "name": "Jeff Z. Pan",
            "link": "https://scholar.google.com/citations?user=zLDAY8QAAAAJ&hl=en",
            "serpapi_link": "https://serpapi.com/search.json?author_id=zLDAY8QAAAAJ&engine=google_scholar_author&hl=en&num=100&start=0",
            "author_id": "zLDAY8QAAAAJ",
            "affiliations": "University of Edinburgh",
            "email": "Verified email at ed.ac.uk",
            "thumbnail": "https://scholar.googleusercontent.com/citations?view_op=small_photo&user=zLDAY8QAAAAJ&citpid=2"
        },
        {
            "name": "Chang Liu",
            "link": "https://scholar.google.com/citations?user=Zrbs8hIAAAAJ&hl=en",
            "serpapi_link": "https://serpapi.com/search.json?author_id=Zrbs8hIAAAAJ&engine=google_scholar_author&hl=en&num=100&start=0",
            "author_id": "Zrbs8hIAAAAJ",
            "affiliations": "Quant Researcher, Citadel Securities",
            "email": "Verified email at eecs.berkeley.edu",
            "thumbnail": "https://scholar.googleusercontent.com/citations?view_op=small_photo&user=Zrbs8hIAAAAJ&citpid=4"
        },
        {
            "name": "Freddy Lecue",
            "link": "https://scholar.google.com/citations?user=GLByS4gAAAAJ&hl=en",
            "serpapi_link": "https://serpapi.com/search.json?author_id=GLByS4gAAAAJ&engine=google_scholar_author&hl=en&num=100&start=0",
            "author_id": "GLByS4gAAAAJ",
            "affiliations": "Chief AI Scientist, CortAIx @Thales - Montreal, Canada. Former-Accenture, IBM Research, Orange",
            "email": "Verified email at inria.fr",
            "thumbnail": "https://scholar.googleusercontent.com/citations?view_op=small_photo&user=GLByS4gAAAAJ&citpid=3"
        },
        {
            "name": "Jacopo Urbani",
            "link": "https://scholar.google.com/citations?user=5o88MDIAAAAJ&hl=en",
            "serpapi_link": "https://serpapi.com/search.json?author_id=5o88MDIAAAAJ&engine=google_scholar_author&hl=en&num=100&start=0",
            "author_id": "5o88MDIAAAAJ",
            "affiliations": "VU University Amsterdam",
            "email": "Verified email at cs.vu.nl",
            "thumbnail": "https://scholar.google.com/citations/images/avatar_scholar_56.png"
        }
    ]
}