{
    "search_metadata": {
        "id": "6256e5fd24e88e20ed3383b5",
        "status": "Success",
        "json_endpoint": "https://serpapi.com/searches/a0b76b3a72c7a8bd/6256e5fd24e88e20ed3383b5.json",
        "created_at": "2022-04-13 15:02:21 UTC",
        "processed_at": "2022-04-13 15:02:21 UTC",
        "google_scholar_author_url": "https://scholar.google.com/citations?user=Aw_5he8AAAAJ&hl&hl=en&cstart=0&pagesize=100",
        "raw_html_file": "https://serpapi.com/searches/a0b76b3a72c7a8bd/6256e5fd24e88e20ed3383b5.html",
        "total_time_taken": 3.85
    },
    "search_parameters": {
        "engine": "google_scholar_author",
        "author_id": "Aw_5he8AAAAJ&hl",
        "hl": "en",
        "start": 0,
        "num": "100"
    },
    "author": {
        "name": "Payel Mukherjee",
        "affiliations": "Student",
        "email": "No verified email",
        "interests": [
            {
                "title": "Corrole",
                "link": "https://scholar.google.com/citations?view_op=search_authors&hl=en&mauthors=label:corrole",
                "serpapi_link": "https://serpapi.com/search.json?engine=google_scholar_profiles&hl=en&mauthors=label%3Acorrole"
            }
        ],
        "thumbnail": "https://scholar.google.com/citations/images/avatar_scholar_128.png"
    },
    "articles": [
        {
            "title": "Synthesis of urea derivatives via reductive carbon dioxide fixation into contracted porphyrin analogues",
            "link": "https://scholar.google.com/citations?view_op=view_citation&hl=en&user=Aw_5he8AAAAJ&pagesize=100&citation_for_view=Aw_5he8AAAAJ:u5HHmVD_uO8C",
            "citation_id": "Aw_5he8AAAAJ:u5HHmVD_uO8C",
            "authors": "SK Patra, K Sahu, B Patra, DK Sahoo, S Mondal, P Mukherjee, HS Biswal, ...",
            "publication": "Green Chemistry 19 (24), 5772-5776, 2017",
            "cited_by": {
                "value": 8,
                "link": "https://scholar.google.com/scholar?oi=bibs&hl=en&cites=5188985199060613026",
                "serpapi_link": "https://serpapi.com/search.json?cites=5188985199060613026&engine=google_scholar&hl=en",
                "cites_id": "5188985199060613026"
            },
            "year": "2017"
        },
        {
            "title": "Grignard Reagent Mediated Demetallation of Silver Corrole Complexes",
            "link": "https://scholar.google.com/citations?view_op=view_citation&hl=en&user=Aw_5he8AAAAJ&pagesize=100&citation_for_view=Aw_5he8AAAAJ:u-x6o8ySG0sC",
            "citation_id": "Aw_5he8AAAAJ:u-x6o8ySG0sC",
            "authors": "B Patra, SK Patra, P Mukherjee, YK Maurya, W Sinha, S Kar",
            "publication": "European Journal of Inorganic Chemistry 2017 (17), 2363-2368, 2017",
            "cited_by": {
                "value": 4,
                "link": "https://scholar.google.com/scholar?oi=bibs&hl=en&cites=7855865447554133477",
                "serpapi_link": "https://serpapi.com/search.json?cites=7855865447554133477&engine=google_scholar&hl=en",
                "cites_id": "7855865447554133477"
            },
            "year": "2017"
        }
    ],
    "cited_by": {
        "table": [
            {
                "citations": {
                    "all": 12,
                    "since_2017": 11
                }
            },
            {
                "h_index": {
                    "all": 2,
                    "since_2017": 2
                }
            },
            {
                "i10_index": {
                    "all": 0,
                    "since_2017": 0
                }
            }
        ],
        "graph": [
            {
                "year": 2018,
                "citations": 2
            },
            {
                "year": 2019,
                "citations": 5
            },
            {
                "year": 2020,
                "citations": 1
            },
            {
                "year": 2021,
                "citations": 2
            },
            {
                "year": 2022,
                "citations": 1
            }
        ]
    },
    "public_access": {
        "link": "https://scholar.google.com/citations?view_op=list_mandates&hl=en&user=Aw_5he8AAAAJ",
        "available": 1,
        "not_available": 0
    }
}